{
    "/js/app.js": "/js/app.js?id=b1a3e6d09f39767db62c",
    "/css/app.css": "/css/app.css?id=ede5f93ec1923421f503",
    "/images/about.svg": "/images/about.svg?id=878ff5005b7369dfab6d",
    "/images/algorithm.svg": "/images/algorithm.svg?id=c34d4d3097ab8bedddb8",
    "/images/catIcon.ico": "/images/catIcon.ico?id=64d7836e72f161924b8e",
    "/images/corporation.svg": "/images/corporation.svg?id=a0661b2cb40c0f28d37d",
    "/images/cover.svg": "/images/cover.svg?id=488326d7f8eef8290b93",
    "/images/desktop.svg": "/images/desktop.svg?id=1316a390cf1dd1b72723",
    "/images/headshot.jpg": "/images/headshot.jpg?id=20f2af6c29b514b14735",
    "/images/IndependentStudy.svg": "/images/IndependentStudy.svg?id=1c42c19ef044a9ead3a7",
    "/images/thesis.svg": "/images/thesis.svg?id=c6b2afdcfbb6b34a97ac",
    "/images/website.svg": "/images/website.svg?id=76c0522280058c8df271"
}
